filedep/__init__.py
filedep/core.py
filedep-0.0.3.dist-info/LICENSE.txt
filedep-0.0.3.dist-info/METADATA
filedep-0.0.3.dist-info/WHEEL
filedep-0.0.3.dist-info/top_level.txt
filedep-0.0.3.dist-info/RECORD
