Metadata-Version: 2.1
Name: filedep
Version: 0.0.3
Summary: filedep: A small python tool to check file dependency
Home-page: https://github.com/flcong/filedep
Author: Francis Cong
Author-email: flcong@outlook.com
License: MIT
Platform: UNKNOWN
License-File: LICENSE.txt
